eth_streams/.DS_Store
eth_streams/__init__.py
eth_streams/context.py
eth_streams/coordinator.py
eth_streams/db.py
eth_streams/logger.py
eth_streams/eth/__init__.py
eth_streams/eth/eth_call_vertex.py
eth_streams/eth/blocks/__init__.py
eth_streams/eth/blocks/publisher.py
eth_streams/eth/blocks/source.py
eth_streams/eth/logs/__init__.py
eth_streams/eth/logs/add_block.py
eth_streams/eth/logs/address_filter.py
eth_streams/eth/logs/contract_event_vertex.py
eth_streams/eth/logs/db_loader.py
eth_streams/eth/logs/signals.py
eth_streams/eth/logs/sources/__init__.py
eth_streams/eth/logs/sources/backfill.py
eth_streams/eth/logs/sources/subscriber.py
eth_streams/eth/logs/vertex/__init__.py
eth_streams/eth/logs/vertex/block_transform.py
eth_streams/eth/logs/vertex/event_vertex.py
eth_streams/models/__init__.py
eth_streams/models/block.py
eth_streams/models/checkpoint.py
eth_streams/models/dex.py
eth_streams/models/events.py
eth_streams/models/transaction.py
eth_streams/pipeline/__init__.py
eth_streams/pipeline/pipeline.py
eth_streams/pipeline/stage.py
eth_streams/pipeline/subscriber.py
eth_streams/pipeline/transformer.py
eth_streams/storage/__init__.py
eth_streams/storage/publisher.py
eth_streams/types/__init__.py
eth_streams/types/address.py
eth_streams/types/annotation.py
eth_streams/types/base.py
eth_streams/types/batch.py
eth_streams/types/callback.py
eth_streams/types/envelope.py
eth_streams/types/events.py
eth_streams/types/measure.py
eth_streams/types/monitor.py
eth_streams/types/sink.py
eth_streams/types/source.py
eth_streams/types/task.py
eth_streams/types/topic.py
eth_streams/types/vertex.py
eth_streams/utils/__init__.py
eth_streams/utils/db.py
eth_streams/utils/expiring_dict.py
eth_streams/utils/implicits.py
eth_streams/utils/iterator.py
eth_streams/utils/model.py
eth_streams/workers/__init__.py
eth_streams/workers/batcher.py
eth_streams/workers/combinator.py
eth_streams/workers/counter.py
eth_streams/workers/echo.py
eth_streams/workers/iterator.py
eth_streams_py-0.1.34.dist-info/METADATA
eth_streams_py-0.1.34.dist-info/WHEEL
eth_streams_py-0.1.34.dist-info/top_level.txt
eth_streams_py-0.1.34.dist-info/RECORD
